st_multiselect_custom/__init__.py
st_multiselect_custom/example.py
st_multiselect_custom/frontend/build/asset-manifest.json
st_multiselect_custom/frontend/build/bootstrap.min.css
st_multiselect_custom/frontend/build/index.html
st_multiselect_custom/frontend/build/static/js/main.d6929f00.js
st_multiselect_custom/frontend/build/static/js/main.d6929f00.js.LICENSE.txt
st_multiselect_custom/frontend/build/static/js/main.d6929f00.js.map
cel_multiselect_custom-0.0.2.dist-info/LICENSE
cel_multiselect_custom-0.0.2.dist-info/METADATA
cel_multiselect_custom-0.0.2.dist-info/WHEEL
cel_multiselect_custom-0.0.2.dist-info/top_level.txt
cel_multiselect_custom-0.0.2.dist-info/RECORD
